pyracing/__init__.py
pyracing/client.py
pyracing/constants.py
pyracing/helpers.py
pyracing/exceptions/__init__.py
pyracing/exceptions/authentication_error.py
pyracing/response_objects/__init__.py
pyracing/response_objects/career_stats.py
pyracing/response_objects/chart_data.py
pyracing/response_objects/historical_data.py
pyracing/response_objects/iracing_data.py
pyracing/response_objects/league_data.py
pyracing/response_objects/session_data.py
pyracing/response_objects/upcoming_events.py
pyracing-0.1.4.dist-info/LICENSE
pyracing-0.1.4.dist-info/METADATA
pyracing-0.1.4.dist-info/WHEEL
pyracing-0.1.4.dist-info/top_level.txt
pyracing-0.1.4.dist-info/RECORD
